mimeo/__init__.py
mimeo/_version.py
mimeo/app.py
mimeo/logs.py
mimeo/run_filter.py
mimeo/run_interspecies.py
mimeo/run_map.py
mimeo/run_self.py
mimeo/utils.py
mimeo/wrappers.py
mimeo-1.2.1.dist-info/METADATA
mimeo-1.2.1.dist-info/WHEEL
mimeo-1.2.1.dist-info/entry_points.txt
mimeo-1.2.1.dist-info/licenses/LICENSE
mimeo-1.2.1.dist-info/RECORD
