Metadata-Version: 2.4
Name: mimeo
Version: 1.2.1
Summary: Scan genomes for internally repeated sequences, elements which are repetitive in another species, or high-identity HGT candidate regions between species.
Project-URL: homepage, https://github.com/adamtaranto/mimeo
Project-URL: documentation, https://github.com/adamtaranto/mimeo
Project-URL: repository, https://github.com/adamtaranto/mimeo
Author: Adam Taranto
License: MIT
License-File: LICENSE
Classifier: Intended Audience :: Science/Research
Classifier: Programming Language :: Python :: 3
Classifier: Topic :: Scientific/Engineering :: Bio-Informatics
Requires-Python: >=3.8
Requires-Dist: biopython>=1.70
Requires-Dist: pandas>=0.20.3
Requires-Dist: rich
Provides-Extra: dev
Requires-Dist: hatch; extra == 'dev'
Requires-Dist: ipykernel; extra == 'dev'
Requires-Dist: isort; extra == 'dev'
Requires-Dist: mkdocs; extra == 'dev'
Requires-Dist: mkdocs-jupyter; extra == 'dev'
Requires-Dist: mkdocs-material; extra == 'dev'
Requires-Dist: mkdocstrings; extra == 'dev'
Requires-Dist: mkdocstrings-python; extra == 'dev'
Requires-Dist: notebook; extra == 'dev'
Requires-Dist: numpydoc-validation; extra == 'dev'
Requires-Dist: pre-commit; extra == 'dev'
Requires-Dist: pymdown-extensions; extra == 'dev'
Requires-Dist: pytest; extra == 'dev'
Requires-Dist: pytest-cov; extra == 'dev'
Requires-Dist: ruff; extra == 'dev'
